args.py
cli.py
config.py
controller.py
helpers.py
model.py
aegis_web3_cli-0.0.2.dist-info/LICENSE
aegis_web3_cli-0.0.2.dist-info/METADATA
aegis_web3_cli-0.0.2.dist-info/WHEEL
aegis_web3_cli-0.0.2.dist-info/entry_points.txt
aegis_web3_cli-0.0.2.dist-info/RECORD
