Metadata-Version: 2.1
Name: aegis-web3-cli
Version: 0.0.2
Summary: 
Requires-Python: >=3.11,<4.0
Classifier: Programming Language :: Python :: 3
Classifier: Programming Language :: Python :: 3.11
Classifier: Programming Language :: Python :: 3.12
Requires-Dist: accelerate (>=0.26.1,<0.27.0)
Requires-Dist: bitsandbytes (>=0.42.0,<0.43.0)
Requires-Dist: clidantic (>=0.1.0,<0.2.0)
Requires-Dist: colorama (>=0.4.6,<0.5.0)
Requires-Dist: ctransformers (>=0.2.27,<0.3.0)
Requires-Dist: datasets (>=2.16.1,<3.0.0)
Requires-Dist: hexbytes (>=0.2.3,<0.3.0)
Requires-Dist: inquirer (>=3.2.3,<4.0.0)
Requires-Dist: numpy (>=1.26.3,<2.0.0)
Requires-Dist: py-solc-x (>=2.0.2,<3.0.0)
Requires-Dist: pydantic (==1.10.14)
Requires-Dist: pyevmasm (>=0.2.3,<0.3.0)
Requires-Dist: scikit-learn (>=1.4.0,<2.0.0)
Requires-Dist: slither (>=0.3.0,<0.4.0)
Requires-Dist: solc (>=0.0.0a0,<0.0.1)
Requires-Dist: torch (>=2.2.0,<3.0.0)
Requires-Dist: torchvision (>=0.17.0,<0.18.0)
Requires-Dist: transformers[torch] (>=4.37.2,<5.0.0)
